<?xml version="1.0" encoding="UTF-8" standalone="yes"?>



<item>
<title>[COLOR lime]•[/COLOR] El Dorado </title>
<link>plugin://plugin.video.elementum/play?uri=https://github.com/brujotv/repo-naranjitos/blob/master/torrentsdepaginas/1-1966.torrent?raw=true</link>
<thumbnail>https://i.imgur.com/2Uk37Wh.jpg</thumbnail>
<fanart>https://i.imgur.com/tjtZg0B.jpg</fanart>
<genre>western.</genre>
<year>1966</year>
<info>Un pistolero llamado Cole Thornton (John Wayne) acude a El Dorado por encargo de poderoso terrateniente, Bart Jason. El cacique le ofrece un trabajo: expulsar de unas tierras próximas a una familia de granjeros, los McDonald. Thornton acaba rechazando el encargo a instancias de Jean Paul Harrah (Robert Mitchum), el sheriff de El Dorado y viejo amigo de Cole. Tiempo después, Thornton se entera de que otro pistolero ha aceptado el trabajo que él rechazó, asi que decide regresar al pueblo para defender a los granjeros y ayudar a su amigo Harrah, que tiene problemas con la bebida. Le acompaña Mississippi (James Caan), un joven habilidoso con el cuchillo.</info>
</item>

<item>
<title>[COLOR lime]•[/COLOR] El bueno, el feo y el malo </title>
<link>plugin://plugin.video.elementum/play?uri=https://github.com/brujotv/repo-naranjitos/blob/master/torrentsdepaginas/2-1966.torrent?raw=true</link>
<thumbnail>https://i.imgur.com/vPG7ok8.jpg</thumbnail>
<fanart>https://i.imgur.com/h0dpjPg.jpg</fanart>
<genre>Western</genre>
<year>1966</year>
<info>Durante la guerra civil norteamericana (1861-1865), tres cazadores de recompensas buscan un tesoro que ninguno de ellos puede encontrar sin la ayuda de los otros dos. Así que colaboran entre sí para conseguir el botín. </info> 
</item>